transmaths.py
transmaths-0.1.dev2.dist-info/DESCRIPTION.rst
transmaths-0.1.dev2.dist-info/METADATA
transmaths-0.1.dev2.dist-info/RECORD
transmaths-0.1.dev2.dist-info/WHEEL
transmaths-0.1.dev2.dist-info/metadata.json
transmaths-0.1.dev2.dist-info/top_level.txt
